plomp/__init__.py
plomp/_buffer_items.py
plomp/_core.py
plomp/_progress.py
plomp/_query.py
plomp/_types.py
plomp/resources/__init__.py
plomp/resources/__pycache__/__init__.cpython-310.pyc
plomp/resources/__pycache__/__init__.cpython-311.pyc
plomp/resources/templates/__init__.py
plomp/resources/templates/index.html
plomp/resources/templates/__pycache__/__init__.cpython-310.pyc
plomp/resources/templates/__pycache__/__init__.cpython-311.pyc
plomp-0.1.4.dist-info/METADATA
plomp-0.1.4.dist-info/WHEEL
plomp-0.1.4.dist-info/top_level.txt
plomp-0.1.4.dist-info/RECORD
