Metadata-Version: 2.4
Name: plomp
Version: 0.1.4
Summary: Plomp Python Module
Author-email: Michael Giba <michaelgiba@gmail.com>
License: MIT
Project-URL: Homepage, https://github.com/michaelgiba/plomp
Project-URL: Bug Tracker, https://github.com/michaelgiba/plomp/issues
Classifier: Programming Language :: Python :: 3
Classifier: Programming Language :: Python :: 3.10
Classifier: Programming Language :: Python :: 3.11
Classifier: License :: OSI Approved :: MIT License
Classifier: Operating System :: OS Independent
Requires-Python: >=3.10
Requires-Dist: typeguard
Provides-Extra: dev
Requires-Dist: pytest>=6.0; extra == "dev"
Requires-Dist: pytest-cov>=2.12; extra == "dev"
Requires-Dist: ruff>=0.11.3; extra == "dev"
Requires-Dist: mypy>=0.950; extra == "dev"
